{
  "statistical_data": {
    "friends_num": 12,
    "active_num": 9,
    "error_num": 3,
    "article_num": 45,
    "last_updated_time": "2026-01-04 12:54:14"
  },
  "article_data": [
    {
      "title": "Paper Reading: Embodied AI 9",
      "created": "2026-01-03 08:00",
      "link": "https://axi404.top/blog/paper-reading-eai9",
      "author": "Axi's Blog",
      "avatar": "https://axi404.top/avatar/avatar.png"
    },
    {
      "title": "Java 内存模型",
      "created": "2026-01-03 00:00",
      "link": "https://mofan212.github.io/posts/Java-Memory-Model/",
      "author": "默烦",
      "avatar": "https://mofan212.github.io/img/avatar.webp"
    },
    {
      "title": "字节码与类加载",
      "created": "2026-01-02 00:00",
      "link": "https://mofan212.github.io/posts/Java-Bytecode-And-Class-Loading/",
      "author": "默烦",
      "avatar": "https://mofan212.github.io/img/avatar.webp"
    },
    {
      "title": "2025 年终总结",
      "created": "2026-01-01 08:00",
      "link": "https://axi404.top/blog/2025",
      "author": "Axi's Blog",
      "avatar": "https://axi404.top/avatar/avatar.png"
    },
    {
      "title": "2025 年末回顾 - Anything different is good",
      "created": "2025-12-31 21:03",
      "link": "https://www.pseudoyu.com/posts/yearly_review_2025",
      "author": "pseudoyu",
      "avatar": "https://www.pseudoyu.com/avatar.webp"
    },
    {
      "title": "认知觉醒",
      "created": "2025-12-29 00:00",
      "link": "https://mofan212.github.io/posts/ren-zhi-jue-xing/",
      "author": "默烦",
      "avatar": "https://mofan212.github.io/img/avatar.webp"
    },
    {
      "title": "大三回忆录",
      "created": "2025-12-27 08:00",
      "link": "https://axi404.top/blog/uni-memoir3",
      "author": "Axi's Blog",
      "avatar": "https://axi404.top/avatar/avatar.png"
    },
    {
      "title": "我在2026年推荐的Mac软件",
      "created": "2025-12-25 18:39",
      "link": "https://blog.zhheo.com/p/vtyyrfd3.html",
      "author": "张洪Heo",
      "avatar": "https://img.zhheo.com/i/67d8fa75943e4.webp"
    },
    {
      "title": "在Mac上使用快捷指令解决：已损坏，无法打开。你应该将它移到废纸篓",
      "created": "2025-12-24 10:41",
      "link": "https://blog.zhheo.com/p/tsk1v2fy.html",
      "author": "张洪Heo",
      "avatar": "https://img.zhheo.com/i/67d8fa75943e4.webp"
    },
    {
      "title": "如何移除Mac中访达多余的菜单项？还你一个清爽的访达右键菜单",
      "created": "2025-12-23 17:35",
      "link": "https://blog.zhheo.com/p/hiubxt8w.html",
      "author": "张洪Heo",
      "avatar": "https://img.zhheo.com/i/67d8fa75943e4.webp"
    },
    {
      "title": "提示 SMS Fee 无法登录怎么办，绕过 SMS Fee 方法",
      "created": "2025-12-23 09:51",
      "link": "https://blog.zhheo.com/p/41n5tavc.html",
      "author": "张洪Heo",
      "avatar": "https://img.zhheo.com/i/67d8fa75943e4.webp"
    },
    {
      "title": "从iPhone13Pro换到iPhone17，我的iPhone17上手体验",
      "created": "2025-12-22 10:36",
      "link": "https://blog.zhheo.com/p/1rb05exh.html",
      "author": "张洪Heo",
      "avatar": "https://img.zhheo.com/i/67d8fa75943e4.webp"
    },
    {
      "title": "为什么我们总是在防御",
      "created": "2025-12-21 00:00",
      "link": "https://mofan212.github.io/posts/Why-Do-I-Do-That/",
      "author": "默烦",
      "avatar": "https://mofan212.github.io/img/avatar.webp"
    },
    {
      "title": "MUSIC | 一则小制作 EP.Paradox of Recurrence",
      "created": "2025-12-19 09:34",
      "link": "https://colinchins.github.io/post/music-or-paradox-of-recurrence/",
      "author": "KELIN’S RECORDS",
      "avatar": "https://kelin.asia/images/avatar.png?v=1766457441145"
    },
    {
      "title": "PostBuild With ESBuild & Minify-HTML",
      "created": "2025-12-19 00:00",
      "link": "https://vluv.space/post-build/",
      "author": "GnixAij",
      "avatar": "https://assets.vluv.space/avatar.webp"
    },
    {
      "title": "周报 #104 - 被遗忘的生活一隅",
      "created": "2025-12-14 09:54",
      "link": "https://www.pseudoyu.com/posts/weekly_review_104",
      "author": "pseudoyu",
      "avatar": "https://www.pseudoyu.com/avatar.webp"
    },
    {
      "title": "周报 #103 - 工作随想与被吞噬的生活",
      "created": "2025-12-02 10:40",
      "link": "https://www.pseudoyu.com/posts/weekly_review_103",
      "author": "pseudoyu",
      "avatar": "https://www.pseudoyu.com/avatar.webp"
    },
    {
      "title": "Use Bun Link for Package Development",
      "created": "2025-12-02 00:00",
      "link": "https://vluv.space/bun_link/",
      "author": "GnixAij",
      "avatar": "https://assets.vluv.space/avatar.webp"
    },
    {
      "title": "月记·二零二五·十一月",
      "created": "2025-12-01 08:00",
      "link": "https://axi404.top/blog/journal-2511",
      "author": "Axi's Blog",
      "avatar": "https://axi404.top/avatar/avatar.png"
    },
    {
      "title": "月记·二零二五·十月",
      "created": "2025-12-01 08:00",
      "link": "https://axi404.top/blog/journal-2510",
      "author": "Axi's Blog",
      "avatar": "https://axi404.top/avatar/avatar.png"
    },
    {
      "title": "被讨厌的勇气",
      "created": "2025-11-30 00:00",
      "link": "https://mofan212.github.io/posts/The-Courage-to-Be-Disliked/",
      "author": "默烦",
      "avatar": "https://mofan212.github.io/img/avatar.webp"
    },
    {
      "title": "Optimize Shiki's HTML Output With styleToClass Transformer",
      "created": "2025-11-30 00:00",
      "link": "https://vluv.space/shiki_style_to_class/",
      "author": "GnixAij",
      "avatar": "https://assets.vluv.space/avatar.webp"
    },
    {
      "title": "Implement Inline Code Highlighting With Markdown-It & Shiki",
      "created": "2025-11-21 00:00",
      "link": "https://vluv.space/inline_code_highlight/",
      "author": "GnixAij",
      "avatar": "https://assets.vluv.space/avatar.webp"
    },
    {
      "title": "OpenWrt固件编译",
      "created": "2025-11-19 08:00",
      "link": "https://emohe.cn/posts/36/",
      "author": "阿涛の小破站",
      "avatar": "https://blog.emohe.cn/favicon.ico"
    },
    {
      "title": "Beyond Catppuccin: Implementing a Multi-Theme System With CSS Variables and Shiki",
      "created": "2025-11-18 00:00",
      "link": "https://vluv.space/web_theme/",
      "author": "GnixAij",
      "avatar": "https://assets.vluv.space/avatar.webp"
    },
    {
      "title": "家庭网络之旁路由配置总结",
      "created": "2025-11-14 08:00",
      "link": "https://emohe.cn/posts/35/",
      "author": "阿涛の小破站",
      "avatar": "https://blog.emohe.cn/favicon.ico"
    },
    {
      "title": "周报 #102 - 我是如何使用 AI 的",
      "created": "2025-10-28 02:38",
      "link": "https://www.pseudoyu.com/posts/weekly_review_102",
      "author": "pseudoyu",
      "avatar": "https://www.pseudoyu.com/avatar.webp"
    },
    {
      "title": "周报 #101 - 消失了三个月，我的生活发生了什么变化",
      "created": "2025-10-20 09:41",
      "link": "https://www.pseudoyu.com/posts/weekly_review_101",
      "author": "pseudoyu",
      "avatar": "https://www.pseudoyu.com/avatar.webp"
    },
    {
      "title": "我认识中的拉康派治疗",
      "created": "2025-10-09 20:33",
      "link": "https://colinchins.github.io/post/sui-xiang-or-rui-ping-la-kang-pai-jing-shen-fen-xi/",
      "author": "KELIN’S RECORDS",
      "avatar": "https://kelin.asia/images/avatar.png?v=1766457441145"
    },
    {
      "title": "解决UFW无法管理Docker映射端口的问题",
      "created": "2025-09-21 08:00",
      "link": "https://emohe.cn/posts/34/",
      "author": "阿涛の小破站",
      "avatar": "https://blog.emohe.cn/favicon.ico"
    },
    {
      "title": "香橙派开发板折腾日记",
      "created": "2025-09-06 08:00",
      "link": "https://emohe.cn/posts/33/",
      "author": "阿涛の小破站",
      "avatar": "https://blog.emohe.cn/favicon.ico"
    },
    {
      "title": "觉醒叙事的表演性",
      "created": "2025-08-28 20:01",
      "link": "https://colinchins.github.io/post/sui-xiang-or-zhui-xun-zi-you-jiu-hao-liao-bu-zhi-yu-dian-ji-rang-ta-zhe-dian-ji-ni-zi-you-bu-zi-you/",
      "author": "KELIN’S RECORDS",
      "avatar": "https://kelin.asia/images/avatar.png?v=1766457441145"
    },
    {
      "title": "linux服务器免密ssh连接教程",
      "created": "2025-08-12 08:00",
      "link": "https://emohe.cn/posts/31/",
      "author": "阿涛の小破站",
      "avatar": "https://blog.emohe.cn/favicon.ico"
    },
    {
      "title": "Go 后端工程师成神之路",
      "created": "2025-07-01 00:00",
      "link": "https://www.penjc.cn/posts/go-roadmap",
      "author": "澄健",
      "avatar": "https://blog.penjc.cn/favicon/logo-512x512.png"
    },
    {
      "title": "接口签名验证完全指南",
      "created": "2025-06-17 00:00",
      "link": "https://www.penjc.cn/posts/sign",
      "author": "澄健",
      "avatar": "https://blog.penjc.cn/favicon/logo-512x512.png"
    },
    {
      "title": "Categorize Your Dependencies",
      "created": "2025-04-28 22:00",
      "link": "https://antfu.me/posts/categorize-deps",
      "author": "Anthony Fu",
      "avatar": "https://antfu.me/avatar.png"
    },
    {
      "title": "Hello Tokyo!",
      "created": "2025-04-08 08:00",
      "link": "https://antfu.me/posts/hello-tokyo",
      "author": "Anthony Fu",
      "avatar": "https://antfu.me/avatar.png"
    },
    {
      "title": "Photos Page",
      "created": "2025-03-12 20:00",
      "link": "https://antfu.me/posts/photos-page",
      "author": "Anthony Fu",
      "avatar": "https://antfu.me/avatar.png"
    },
    {
      "title": "线程安全问题",
      "created": "2025-03-04 00:00",
      "link": "https://www.penjc.cn/posts/thread-safe",
      "author": "澄健",
      "avatar": "https://blog.penjc.cn/favicon/logo-512x512.png"
    },
    {
      "title": "Async, Sync, in Between",
      "created": "2025-03-03 08:00",
      "link": "https://antfu.me/posts/async-sync-in-between",
      "author": "Anthony Fu",
      "avatar": "https://antfu.me/avatar.png"
    },
    {
      "title": "ThreadLocal 详解",
      "created": "2025-02-24 00:00",
      "link": "https://www.penjc.cn/posts/threadLocal",
      "author": "澄健",
      "avatar": "https://blog.penjc.cn/favicon/logo-512x512.png"
    },
    {
      "title": "并发编程基础",
      "created": "2025-02-16 00:00",
      "link": "https://www.penjc.cn/posts/java-concurrent",
      "author": "澄健",
      "avatar": "https://blog.penjc.cn/favicon/logo-512x512.png"
    },
    {
      "title": "Move on to ESM-only",
      "created": "2025-02-05 08:00",
      "link": "https://antfu.me/posts/move-on-to-esm-only",
      "author": "Anthony Fu",
      "avatar": "https://antfu.me/avatar.png"
    },
    {
      "title": "随想 | 民科看精神分析工作的形式",
      "created": "2025-02-02 11:08",
      "link": "https://colinchins.github.io/post/sui-xiang-or-min-ke-kan-jing-shen-fen-xi-gong-zuo-de-xing-shi/",
      "author": "KELIN’S RECORDS",
      "avatar": "https://kelin.asia/images/avatar.png?v=1766457441145"
    },
    {
      "title": "随想 | UC高达剧本的悲哀",
      "created": "2024-10-28 19:44",
      "link": "https://colinchins.github.io/post/shan-guang-de-ha-sa-wei/",
      "author": "KELIN’S RECORDS",
      "avatar": "https://kelin.asia/images/avatar.png?v=1766457441145"
    }
  ]
}